gadwall.py
gadwall-0.2.0.dist-info/LICENSE
gadwall-0.2.0.dist-info/METADATA
gadwall-0.2.0.dist-info/WHEEL
gadwall-0.2.0.dist-info/top_level.txt
gadwall-0.2.0.dist-info/RECORD
