Metadata-Version: 2.1
Name: gadwall
Version: 0.2.0
Summary: A command line client to duckdb
Home-page: https://github.com/tebeka/gadwall
Author: Miki Tebeka
Author-email: miki.tebeka@gmail.com
Classifier: Programming Language :: Python :: 3
Classifier: License :: OSI Approved :: MIT License
Classifier: Operating System :: OS Independent
Requires-Python: >=3.6
License-File: LICENSE
Requires-Dist: duckdb (>=0.4.0)
